{"mappa30x30":[
  {"fifo_base":
    {
      "hdefault":{
        "penalty":10763,
        "number-plane-reused":1,
        "number-order":9,
        "order-performed":7
      },
      "hsimple":{
        "penalty":13352,
        "number-plane-reused":0,
        "number-order":20,
        "order-performed":12
      },
      "hhard":{
        "penalty":49344,
        "number-plane-reused":5,
        "number-order":20,
        "order-performed":12
      },
      "hperson1":{
        "penalty":NAN,
        "number-plane-reused":,
        "number-order":,
        "order-performed":
      },
      "hperson2":{
        "penalty":NAN,
        "number-plane-reused":,
        "number-order":,
        "order-performed":
      },
      "hcheckf":{
        "penalty":26142,
        "number-plane-reused":7,
        "number-order":21,
        "order-performed":20
      }
    }
  },
  {"fifo_pro":
    {
      "hdefault":{
        "penalty":10763,
        "number-plane-reused":1,
        "number-order":9,
        "order-performed":7
      },
      "hsimple":{
        "penalty":13352,
        "number-plane-reused":0,
        "number-order":20,
        "order-performed":12
      },
      "hhard":{
        "penalty":49344,
        "number-plane-reused":5,
        "number-order":20,
        "order-performed":12
      },
      "hperson1":{
        "penalty":28816,
        "number-plane-reused":1,
        "number-order":20,
        "order-performed":12
      },
      "hperson2":{
        "penalty":27495,
        "number-plane-reused":4,
        "number-order":20,
        "order-performed":12
      },
      "hcheckf":{
        "penalty":26142,
        "number-plane-reused":7,
        "number-order":21,
        "order-performed":20
      }
    }
  },
  {"low_penalty":
    {
      "hdefault":{
        "penalty":8737,
        "number-plane-reused":1,
        "number-order":9,
        "order-performed":7
      },
      "hsimple":{
        "penalty":13041,
        "number-plane-reused":1,
        "number-order":20,
        "order-performed":13
      },
      "hhard":{
        "penalty":53459,
        "number-plane-reused":6,
        "number-order":20,
        "order-performed":12
      },
      "hperson1":{
        "penalty":27850,
        "number-plane-reused":1,
        "number-order":20,
        "order-performed":12
      },
      "hperson2":{
        "penalty":29675,
        "number-plane-reused":0,
        "number-order":20,
        "order-performed":12
      },
      "hcheckf":{
        "penalty":20737,
        "number-plane-reused":6,
        "number-order":21,
        "order-performed":20
      }
    }
  },
  {"pendist":
    {
      "hdefault":{
        "penalty":8229,
        "number-plane-reused":2,
        "number-order":9,
        "order-performed":7
      },
      "hsimple":{
        "penalty":14064,
        "number-plane-reused":1,
        "number-order":20,
        "order-performed":13
      },
      "hhard":{
        "penalty":51219,
        "number-plane-reused":3,
        "number-order":20,
        "order-performed":12
      },
      "hperson1":{
        "penalty":24781,
        "number-plane-reused":2,
        "number-order":20,
        "order-performed":12
      },
      "hperson2":{
        "penalty":25809,
        "number-plane-reused":4,
        "number-order":20,
        "order-performed":12
      },
      "hcheckf":{
        "penalty":17602,
        "number-plane-reused":6,
        "number-order":21,
        "order-performed":20
      }
    }
  },
  {"hard":
    {
      "hdefault":{
        "penalty":8267,
        "number-plane-reused":0,
        "number-order":9,
        "order-performed":7
      },
      "hsimple":{
        "penalty":14064,
        "number-plane-reused":0,
        "number-order":20,
        "order-performed":12
      },
      "hhard":{
        "penalty":83925,
        "number-plane-reused":9,
        "number-order":20,
        "order-performed":12
      },
      "hperson1":{
        "penalty":34531,
        "number-plane-reused":2,
        "number-order":20,
        "order-performed":12
      },
      "hperson2":{
        "penalty":33861,
        "number-plane-reused":2,
        "number-order":20,
        "order-performed":12
      },
      "hcheckf":{
        "penalty":12490,
        "number-plane-reused":5,
        "number-order":21,
        "order-performed":21
      }
    }
  }
  ]
}
